dotrunner/__init__.py
dotrunner/dotrunner.py
dotrunner/version.py
dotrunner-0.1.15.data/data/LICENSE
dotrunner-0.1.15.data/data/README.md
dotrunner-0.1.15.data/data/README.rst
tests/snapshots/__init__.py
tests/snapshots/snap_dotrunner_test.py
dotrunner-0.1.15.dist-info/LICENSE
dotrunner-0.1.15.dist-info/METADATA
dotrunner-0.1.15.dist-info/WHEEL
dotrunner-0.1.15.dist-info/entry_points.txt
dotrunner-0.1.15.dist-info/top_level.txt
dotrunner-0.1.15.dist-info/RECORD
