Metadata-Version: 2.1
Name: dotrunner
Version: 0.1.15
Summary: Links dotfiles
Home-page: https://github.com/jondot/dotrunner
Author: Dotan Nahum
Author-email: jondotan@gmail.com
License: Copyright (c) 2012, Kenneth Reitz
Requires-Dist: toolz
Requires-Dist: docopt
Requires-Dist: networkx
Requires-Dist: pyyaml
Requires-Dist: delegator.py
Requires-Dist: colorama
Requires-Dist: pyspin
